findfeed/__init__.py
findfeed/crawler/__init__.py
findfeed/crawler/crawler.py
findfeed/crawler/duplicatefilter.py
findfeed/crawler/item.py
findfeed/crawler/item_parser.py
findfeed/crawler/lib.py
findfeed/crawler/queueable.py
findfeed/crawler/request.py
findfeed/crawler/response.py
findfeed/crawler/trace.py
findfeed/feed_spider/__init__.py
findfeed/feed_spider/dupefilter.py
findfeed/feed_spider/favicon.py
findfeed/feed_spider/feed_info.py
findfeed/feed_spider/feed_info_parser.py
findfeed/feed_spider/lib.py
findfeed/feed_spider/link_filter.py
findfeed/feed_spider/regexes.py
findfeed/feed_spider/site_meta.py
findfeed/feed_spider/site_meta_parser.py
findfeed/feed_spider/spider.py
findfeed-1.0.0.dist-info/METADATA
findfeed-1.0.0.dist-info/WHEEL
findfeed-1.0.0.dist-info/licenses/LICENSE
findfeed-1.0.0.dist-info/RECORD
