Metadata-Version: 2.4
Name: findfeed
Version: 1.0.0
Summary: RSS feed finder utility
Project-URL: Homepage, https://github.com/gperdrizet/feedsearch-crawler
Author-email: George Perdrizet <george@perdrizet.org>
License-File: LICENSE
Requires-Python: >=3.10
Requires-Dist: aiohttp
Requires-Dist: bs4
Requires-Dist: feedparser
Requires-Dist: python-dateutil
Requires-Dist: w3lib
Requires-Dist: yarl
